esoc_events/__init__.py
esoc_events/py.typed
esoc_events/utils/__init__.py
esoc_events/utils/abstract_parser.py
esoc_events/utils/evfm_parser.py
esoc_events/utils/evtc_parser.py
esoc_events/utils/fecs_parser.py
esoc_events/utils/plnview_parser.py
esoc_events/utils/time.py
esoc_events/utils/uevt_parser.py
esoc_events/utils/uevt_writer.py
esoc_events/utils/xml.py
esoc_events-0.0.3.dist-info/WHEEL
esoc_events-0.0.3.dist-info/METADATA
esoc_events-0.0.3.dist-info/RECORD
