Metadata-Version: 2.1
Name: esoc-events
Version: 0.0.3
Summary: Querying events comming from ESOC sources
Home-page: https://r-andres.github.io/esoc_events
License: MIT
Author: Rafael Andres
Author-email: r.andres.blasco@gmail.com
Requires-Python: >=3.9,<4.0
Classifier: Development Status :: 4 - Beta
Classifier: Intended Audience :: Developers
Classifier: License :: OSI Approved :: MIT License
Classifier: Operating System :: OS Independent
Classifier: Programming Language :: Python
Classifier: Programming Language :: Python :: 3
Classifier: Programming Language :: Python :: 3.9
Classifier: Programming Language :: Python :: 3.10
Classifier: Programming Language :: Python :: 3.11
Classifier: Programming Language :: Python :: 3
Classifier: Programming Language :: Python :: 3.7
Classifier: Programming Language :: Python :: 3.8
Classifier: Programming Language :: Python :: 3.9
Classifier: Topic :: Software Development :: Libraries :: Python Modules
Classifier: Typing :: Typed
Requires-Dist: pytest-html (>=4.1.1,<5.0.0)
Project-URL: Documentation, https://r-andres.github.io/esoc_events
Project-URL: Repository, https://github.com/r-andres/esoc_events
